{"2025":1,"debouncing":1,"throttling":1,"event":1,"최적화":1,"image":1,"component":1,"react":5,"next":5,"javascript":4,"class":2,"function":1,"typescript":2,"style":3,"css":5,"light":1,"dark":1,"theme":2,"npm":2,"npx":1,"node":3,"package":3,"autoprefixer":1,"postcss":1,"tailwindcss":2,"compile":1,"hook":2,"useref":1,"source":2,"font":2,"text":1,"wrap":1,"balance":1,"pretty":1,"git":1,"branch":1,"rename":1,"clsx":1,"favicon":1,"icon":1,"pwa":1,"plugin":1,"extension":1,"library":1,"jsx":1,"attribute":1,"conditional":1,"link":1,"mobile":1,"meta":2,"viewport":1,"keyboard":1,"nextjs":1,"astro":1,"remix":1,"framework":1,"seo":1,"params":1,"build":1,"type":1,"error":1,"version":1,"update":1,"animation":1,"scroll":1,"scale":1,"svg":1,"svgr":1,"svgo":1,"use":1,"input":1,"valid":1,"user-invalid":1,"form":1}